[
    {
        "code_barre": "3017620422003",
        "nom": "Huile de palme 1L",
        "prix_unitaire_ht": 1200,
        "quantite_stock": 30,
        "date_expiration": "2026-12-31",
        "date_enregistrement": "2026-04-17"
    },
    {
        "code_barre": "90338052",
        "nom": "COCA BOUTEILLE",
        "prix_unitaire_ht": 1000,
        "quantite_stock": 30,
        "date_expiration": "2026-04-28",
        "date_enregistrement": "2026-04-28"
    },
    {
        "code_barre": "6044000013992",
        "nom": "EDEN EAU",
        "prix_unitaire_ht": 499,
        "quantite_stock": 50,
        "date_expiration": "2028-04-29",
        "date_enregistrement": "2026-04-29"
    }
]